MANIFEST.in
README.rst
setup.py
wcc/__init__.py
wcc/hands.py
wcc/logger.py
wcc/loop_proxydb_evaluation.sh
wcc/mytest.py
wcc/oss.py
wcc/out.log
wcc/pmc.py
wcc/proxy.py
wcc/req.py
wcc/test.py
wcc/urllibx.py
wcc/user_agents.json
wcc/utils.py
wcc/wcc.md
wcc/wcc_qcc_combasic.py
wcc.egg-info/PKG-INFO
wcc.egg-info/SOURCES.txt
wcc.egg-info/dependency_links.txt
wcc.egg-info/requires.txt
wcc.egg-info/top_level.txt
wcc/__pycache__/req.cpython-37.pyc
wcc/test/test.py
wcc/trash/oss.py
wcc/trash/req.py.bak
wcc/trash/requests.py.bak
wcc/trash/user_agent.py
wcc/trash/wcc.py.bak