Metadata-Version: 1.1
Name: wcc
Version: 1.6.5
Summary: Wikicivi WCC (Wikicivi Crawler Client) SDK
Home-page: http://wcc.wikicivi.com
Author: Jiao Shuai
Author-email: jiaoshuaihit@gmail.com
License: UNKNOWN
Platform: UNKNOWN
Classifier: Development Status :: 5 - Production/Stable
Classifier: Intended Audience :: Developers
Classifier: License :: OSI Approved :: MIT License
Classifier: Operating System :: OS Independent
Classifier: Programming Language :: Python
Classifier: Programming Language :: Python :: 3
Classifier: Programming Language :: Python :: 3.3
Classifier: Programming Language :: Python :: 3.4
Classifier: Programming Language :: Python :: 3.5
